snaf/HLA_Allele_frequency_21_populations.csv
snaf/__init__.py
snaf/binding.py
snaf/data_io.py
snaf/downstream.py
snaf/gtex.py
snaf/gtex_viewer.py
snaf/mqpar.xml
snaf/proteomics.py
snaf/snaf.py
snaf/visualize.py
snaf/dash_app/__init__.py
snaf/dash_app/app.py
snaf/dash_app/pweblogo.py
snaf/dash_app/schema.py
snaf/deepimmuno/__init__.py
snaf/deepimmuno/deepimmuno.py
snaf/deepimmuno/data/after_pca.txt
snaf/deepimmuno/data/hla2paratopeTable_aligned.txt
snaf/deepimmuno/models/cnn_model_331_3_7/.data-00000-of-00001
snaf/deepimmuno/models/cnn_model_331_3_7/.index
snaf/deepimmuno/models/cnn_model_331_3_7/checkpoint
snaf/surface/__init__.py
snaf/surface/alignment.py
snaf/surface/api.py
snaf/surface/data_io.py
snaf/surface/emboss.py
snaf/surface/main.py
snaf/surface/orf_check.py
snaf/surface/orf_finder.py
SNAF-0.7.0.dist-info/LICENSE
SNAF-0.7.0.dist-info/METADATA
SNAF-0.7.0.dist-info/WHEEL
SNAF-0.7.0.dist-info/top_level.txt
SNAF-0.7.0.dist-info/RECORD
